{"id": "TMY9Wrh1oPA", "title": "Stevie Ray Vaughan & Double Trouble - Change It (Video)", "formats": [{"asr": 48000, "filesize": 1521616, "format_id": "249", "format_note": "tiny", "fps": null, "height": null, "quality": 0, "tbr": 48.91, "url": "https://rr5---sn-0opoxu-ihv6.googlevideo.com/videoplayback?expire=1670788115&ei=s9-VY5CYB8evkgb_26GYDw&ip=189.173.225.87&id=o-AHQ4p-kGgRd3_FOPkIXVPI_YrfqyMWJmo5WG4F_abcbD&itag=249&source=youtube&requiressl=yes&mh=ma&mm=31%2C29&mn=sn-0opoxu-ihv6%2Csn-q4fl6nsk&ms=au%2Crdu&mv=m&mvi=5&pcm2cms=yes&pl=24&gcr=mx&initcwndbps=907500&vprv=1&mime=audio%2Fwebm&ns=CdhfWTqhbbY9pU_riB5P3B8J&gir=yes&clen=1521616&dur=248.881&lmt=1540946626051807&mt=1670766317&fvip=2&keepalive=yes&fexp=24001373%2C24007246&c=WEB&txp=5411222&n=4ei-1pL34MiCfe-x2&sparams=expire%2Cei%2Cip%2Cid%2Citag%2Csource%2Crequiressl%2Cgcr%2Cvprv%2Cmime%2Cns%2Cgir%2Cclen%2Cdur%2Clmt&lsparams=mh%2Cmm%2Cmn%2Cms%2Cmv%2Cmvi%2Cpcm2cms%2Cpl%2Cinitcwndbps&lsig=AG3C_xAwRQIhAOXwZ4dtrKVhH5n4qscPheUpm58lAHV9Eds98EtjexZ5AiAvse_oVnu6PXmMaN09YwpfK1igKvQA2JXwH3-8LzmAFQ%3D%3D&sig=AOq0QJ8wRAIgGvuOTS4dIF_yxtfqEQb26pvhci5bbBD0-X5lD95BZawCIEXGldsDWnuZHqbGYJ7S2GEPLFg3YN0eUm_vczLzB-Kv", "width": null, "ext": "webm", "vcodec": "none", "acodec": "opus", "abr": 48.91, "downloader_options": {"http_chunk_size": 10485760}, "container": "webm_dash", "format": "249 - audio only (tiny)", "protocol": "https", "http_headers": {"User-Agent": "Mozilla/5.0 (Windows NT 10.0; Win64; x64) AppleWebKit/537.36 (KHTML, like Gecko) Chrome/72.0.3625.2 Safari/537.36", "Accept-Charset": "ISO-8859-1,utf-8;q=0.7,*;q=0.7", "Accept": "text/html,application/xhtml+xml,application/xml;q=0.9,*/*;q=0.8", "Accept-Encoding": "gzip, deflate", "Accept-Language": "en-us,en;q=0.5"}}, {"asr": 48000, "filesize": 2013672, "format_id": "250", "format_note": "tiny", "fps": null, "height": null, "quality": 0, "tbr": 64.727, "url": "https://rr5---sn-0opoxu-ihv6.googlevideo.com/videoplayback?expire=1670788115&ei=s9-VY5CYB8evkgb_26GYDw&ip=189.173.225.87&id=o-AHQ4p-kGgRd3_FOPkIXVPI_YrfqyMWJmo5WG4F_abcbD&itag=250&source=youtube&requiressl=yes&mh=ma&mm=31%2C29&mn=sn-0opoxu-ihv6%2Csn-q4fl6nsk&ms=au%2Crdu&mv=m&mvi=5&pcm2cms=yes&pl=24&gcr=mx&initcwndbps=907500&vprv=1&mime=audio%2Fwebm&ns=CdhfWTqhbbY9pU_riB5P3B8J&gir=yes&clen=2013672&dur=248.881&lmt=1540946626657360&mt=1670766317&fvip=2&keepalive=yes&fexp=24001373%2C24007246&c=WEB&txp=5411222&n=4ei-1pL34MiCfe-x2&sparams=expire%2Cei%2Cip%2Cid%2Citag%2Csource%2Crequiressl%2Cgcr%2Cvprv%2Cmime%2Cns%2Cgir%2Cclen%2Cdur%2Clmt&lsparams=mh%2Cmm%2Cmn%2Cms%2Cmv%2Cmvi%2Cpcm2cms%2Cpl%2Cinitcwndbps&lsig=AG3C_xAwRQIgJvfWSpgou7Pa9Z7ZBwKVl2S6MocYIY4ape6xmXaTx_QCIQDiDVk65fGusr9duLs2MqX6pptteiw4x4VaxMPKrDie-w%3D%3D&sig=AOq0QJ8wRgIhAPIJDzprrYHBaRjeZBfEPijqhVV0cdrbCDc2VO8Tb3L7AiEAiK6SrVJkCePx84v6OyeE5iB_wZRbATF6bEOdtg0y7Jk=", "width": null, "ext": "webm", "vcodec": "none", "acodec": "opus", "abr": 64.727, "downloader_options": {"http_chunk_size": 10485760}, "container": "webm_dash", "format": "250 - audio only (tiny)", "protocol": "https", "http_headers": {"User-Agent": "Mozilla/5.0 (Windows NT 10.0; Win64; x64) AppleWebKit/537.36 (KHTML, like Gecko) Chrome/72.0.3625.2 Safari/537.36", "Accept-Charset": "ISO-8859-1,utf-8;q=0.7,*;q=0.7", "Accept": "text/html,application/xhtml+xml,application/xml;q=0.9,*/*;q=0.8", "Accept-Encoding": "gzip, deflate", "Accept-Language": "en-us,en;q=0.5"}}, {"asr": 44100, "filesize": 3954050, "format_id": "140", "format_note": "tiny", "fps": null, "height": null, "quality": 0, "tbr": 127.08, "url": "https://rr5---sn-0opoxu-ihv6.googlevideo.com/videoplayback?expire=1670788115&ei=s9-VY5CYB8evkgb_26GYDw&ip=189.173.225.87&id=o-AHQ4p-kGgRd3_FOPkIXVPI_YrfqyMWJmo5WG4F_abcbD&itag=140&source=youtube&requiressl=yes&mh=ma&mm=31%2C29&mn=sn-0opoxu-ihv6%2Csn-q4fl6nsk&ms=au%2Crdu&mv=m&mvi=5&pcm2cms=yes&pl=24&gcr=mx&initcwndbps=907500&vprv=1&mime=audio%2Fmp4&ns=CdhfWTqhbbY9pU_riB5P3B8J&gir=yes&clen=3954050&dur=248.917&lmt=1540944164191728&mt=1670766317&fvip=2&keepalive=yes&fexp=24001373%2C24007246&c=WEB&txp=5432432&n=4ei-1pL34MiCfe-x2&sparams=expire%2Cei%2Cip%2Cid%2Citag%2Csource%2Crequiressl%2Cgcr%2Cvprv%2Cmime%2Cns%2Cgir%2Cclen%2Cdur%2Clmt&lsparams=mh%2Cmm%2Cmn%2Cms%2Cmv%2Cmvi%2Cpcm2cms%2Cpl%2Cinitcwndbps&lsig=AG3C_xAwRQIhAIgiMllL363fHQmEwGzwilNHsQxLN_r-jz8wFRtDnIu6AiBdbTTSLLvUMy4-D38YUddjod-X8oCa684DhZia-RIw3Q%3D%3D&sig=AOq0QJ8wRgIhAN3Mg6EOo2CfLA9nLNWlyeLAzDKCvxoT40rXG17hcAGzAiEA1R3-OjsJHt08lrGoJ9JL7p70s7zAvWGREaJWhNT3a9U=", "width": null, "ext": "m4a", "vcodec": "none", "acodec": "mp4a.40.2", "abr": 127.08, "downloader_options": {"http_chunk_size": 10485760}, "container": "m4a_dash", "format": "140 - audio only (tiny)", "protocol": "https", "http_headers": {"User-Agent": "Mozilla/5.0 (Windows NT 10.0; Win64; x64) AppleWebKit/537.36 (KHTML, like Gecko) Chrome/72.0.3625.2 Safari/537.36", "Accept-Charset": "ISO-8859-1,utf-8;q=0.7,*;q=0.7", "Accept": "text/html,application/xhtml+xml,application/xml;q=0.9,*/*;q=0.8", "Accept-Encoding": "gzip, deflate", "Accept-Language": "en-us,en;q=0.5"}}, {"asr": 48000, "filesize": 4024418, "format_id": "251", "format_note": "tiny", "fps": null, "height": null, "quality": 0, "tbr": 129.36, "url": "https://rr5---sn-0opoxu-ihv6.googlevideo.com/videoplayback?expire=1670788115&ei=s9-VY5CYB8evkgb_26GYDw&ip=189.173.225.87&id=o-AHQ4p-kGgRd3_FOPkIXVPI_YrfqyMWJmo5WG4F_abcbD&itag=251&source=youtube&requiressl=yes&mh=ma&mm=31%2C29&mn=sn-0opoxu-ihv6%2Csn-q4fl6nsk&ms=au%2Crdu&mv=m&mvi=5&pcm2cms=yes&pl=24&gcr=mx&initcwndbps=907500&vprv=1&mime=audio%2Fwebm&ns=CdhfWTqhbbY9pU_riB5P3B8J&gir=yes&clen=4024418&dur=248.881&lmt=1540946628174665&mt=1670766317&fvip=2&keepalive=yes&fexp=24001373%2C24007246&c=WEB&txp=5411222&n=4ei-1pL34MiCfe-x2&sparams=expire%2Cei%2Cip%2Cid%2Citag%2Csource%2Crequiressl%2Cgcr%2Cvprv%2Cmime%2Cns%2Cgir%2Cclen%2Cdur%2Clmt&lsparams=mh%2Cmm%2Cmn%2Cms%2Cmv%2Cmvi%2Cpcm2cms%2Cpl%2Cinitcwndbps&lsig=AG3C_xAwRAIgD_rm3SMp-ZJAygYq8c0eAsbIVtlOIbrVslnFn8qMyY0CIBV4Np6RsPz1DDmfZZKj157kwtHO6WTO3VigpksmVnDK&sig=AOq0QJ8wRQIhAOUT72iAVWqzCUODwTH3V6A3hahpb1WPjwIeuVWyseJMAiALpXZCkJNXA1mwGtlnOpbRZo-0GUK7_qEKVYJCca96ww==", "width": null, "ext": "webm", "vcodec": "none", "acodec": "opus", "abr": 129.36, "downloader_options": {"http_chunk_size": 10485760}, "container": "webm_dash", "format": "251 - audio only (tiny)", "protocol": "https", "http_headers": {"User-Agent": "Mozilla/5.0 (Windows NT 10.0; Win64; x64) AppleWebKit/537.36 (KHTML, like Gecko) Chrome/72.0.3625.2 Safari/537.36", "Accept-Charset": "ISO-8859-1,utf-8;q=0.7,*;q=0.7", "Accept": "text/html,application/xhtml+xml,application/xml;q=0.9,*/*;q=0.8", "Accept-Encoding": "gzip, deflate", "Accept-Language": "en-us,en;q=0.5"}}, {"asr": null, "filesize": 1729419, "format_id": "160", "format_note": "144p", "fps": 30, "height": 144, "quality": 0, "tbr": 55.597, "url": "https://rr5---sn-0opoxu-ihv6.googlevideo.com/videoplayback?expire=1670788115&ei=s9-VY5CYB8evkgb_26GYDw&ip=189.173.225.87&id=o-AHQ4p-kGgRd3_FOPkIXVPI_YrfqyMWJmo5WG4F_abcbD&itag=160&aitags=133%2C134%2C135%2C160%2C242%2C243%2C244%2C278%2C394%2C395%2C396%2C397&source=youtube&requiressl=yes&mh=ma&mm=31%2C29&mn=sn-0opoxu-ihv6%2Csn-q4fl6nsk&ms=au%2Crdu&mv=m&mvi=5&pcm2cms=yes&pl=24&gcr=mx&initcwndbps=907500&vprv=1&mime=video%2Fmp4&ns=CdhfWTqhbbY9pU_riB5P3B8J&gir=yes&clen=1729419&dur=248.848&lmt=1540945209350661&mt=1670766317&fvip=2&keepalive=yes&fexp=24001373%2C24007246&c=WEB&txp=5432432&n=4ei-1pL34MiCfe-x2&sparams=expire%2Cei%2Cip%2Cid%2Caitags%2Csource%2Crequiressl%2Cgcr%2Cvprv%2Cmime%2Cns%2Cgir%2Cclen%2Cdur%2Clmt&lsparams=mh%2Cmm%2Cmn%2Cms%2Cmv%2Cmvi%2Cpcm2cms%2Cpl%2Cinitcwndbps&lsig=AG3C_xAwRAIgQN1Cx4KWisqFMtCCqShYjYwHssYnpTwsXrORjVYhQRcCIHgV68xNckK8m4ZGUw-iLw9sacZCZK92p4O2eZ_XYjBR&sig=AOq0QJ8wRgIhAKbFuIMdMnHRvw9t61TFdEnfb9lSp_q0SvtyLIY7TjbsAiEAyZwIz_6LI-bwc0TmP0gLd0ebQEvYoyLhKF6_YtXMp34=", "width": 192, "ext": "mp4", "vcodec": "avc1.4d400c", "acodec": "none", "vbr": 55.597, "downloader_options": {"http_chunk_size": 10485760}, "container": "mp4_dash", "format": "160 - 192x144 (144p)", "protocol": "https", "http_headers": {"User-Agent": "Mozilla/5.0 (Windows NT 10.0; Win64; x64) AppleWebKit/537.36 (KHTML, like Gecko) Chrome/72.0.3625.2 Safari/537.36", "Accept-Charset": "ISO-8859-1,utf-8;q=0.7,*;q=0.7", "Accept": "text/html,application/xhtml+xml,application/xml;q=0.9,*/*;q=0.8", "Accept-Encoding": "gzip, deflate", "Accept-Language": "en-us,en;q=0.5"}}, {"asr": null, "filesize": 2198491, "format_id": "278", "format_note": "144p", "fps": 30, "height": 144, "quality": 0, "tbr": 70.677, "url": "https://rr5---sn-0opoxu-ihv6.googlevideo.com/videoplayback?expire=1670788115&ei=s9-VY5CYB8evkgb_26GYDw&ip=189.173.225.87&id=o-AHQ4p-kGgRd3_FOPkIXVPI_YrfqyMWJmo5WG4F_abcbD&itag=278&aitags=133%2C134%2C135%2C160%2C242%2C243%2C244%2C278%2C394%2C395%2C396%2C397&source=youtube&requiressl=yes&mh=ma&mm=31%2C29&mn=sn-0opoxu-ihv6%2Csn-q4fl6nsk&ms=au%2Crdu&mv=m&mvi=5&pcm2cms=yes&pl=24&gcr=mx&initcwndbps=907500&vprv=1&mime=video%2Fwebm&ns=CdhfWTqhbbY9pU_riB5P3B8J&gir=yes&clen=2198491&dur=248.848&lmt=1540945237639436&mt=1670766317&fvip=2&keepalive=yes&fexp=24001373%2C24007246&c=WEB&txp=5432432&n=4ei-1pL34MiCfe-x2&sparams=expire%2Cei%2Cip%2Cid%2Caitags%2Csource%2Crequiressl%2Cgcr%2Cvprv%2Cmime%2Cns%2Cgir%2Cclen%2Cdur%2Clmt&lsparams=mh%2Cmm%2Cmn%2Cms%2Cmv%2Cmvi%2Cpcm2cms%2Cpl%2Cinitcwndbps&lsig=AG3C_xAwRQIgTldXxD9JkAQAvX29mwlfpVP3v1k_3DAdZRrAdaF0AScCIQDr4VFW7ok1Xp1k6hCI1V_J6zo730por_0xh4mxCNm5cg%3D%3D&sig=AOq0QJ8wRQIgE2_yN_FB0TQODcLPCuIdra5cwLg4cFw-UyP5eiCWLCECIQDQlCYfbc4YEOXRSKrnnasJkJFqsoJ0Lvgceox-NHCM4g==", "width": 192, "ext": "webm", "vcodec": "vp9", "acodec": "none", "vbr": 70.677, "downloader_options": {"http_chunk_size": 10485760}, "container": "webm_dash", "format": "278 - 192x144 (144p)", "protocol": "https", "http_headers": {"User-Agent": "Mozilla/5.0 (Windows NT 10.0; Win64; x64) AppleWebKit/537.36 (KHTML, like Gecko) Chrome/72.0.3625.2 Safari/537.36", "Accept-Charset": "ISO-8859-1,utf-8;q=0.7,*;q=0.7", "Accept": "text/html,application/xhtml+xml,application/xml;q=0.9,*/*;q=0.8", "Accept-Encoding": "gzip, deflate", "Accept-Language": "en-us,en;q=0.5"}}, {"asr": null, "filesize": 2223748, "format_id": "394", "format_note": "144p", "fps": 30, "height": 144, "quality": 0, "tbr": 71.489, "url": "https://rr5---sn-0opoxu-ihv6.googlevideo.com/videoplayback?expire=1670788115&ei=s9-VY5CYB8evkgb_26GYDw&ip=189.173.225.87&id=o-AHQ4p-kGgRd3_FOPkIXVPI_YrfqyMWJmo5WG4F_abcbD&itag=394&aitags=133%2C134%2C135%2C160%2C242%2C243%2C244%2C278%2C394%2C395%2C396%2C397&source=youtube&requiressl=yes&mh=ma&mm=31%2C29&mn=sn-0opoxu-ihv6%2Csn-q4fl6nsk&ms=au%2Crdu&mv=m&mvi=5&pcm2cms=yes&pl=24&gcr=mx&initcwndbps=907500&vprv=1&mime=video%2Fmp4&ns=CdhfWTqhbbY9pU_riB5P3B8J&gir=yes&clen=2223748&dur=248.848&lmt=1631309330136549&mt=1670766317&fvip=2&keepalive=yes&fexp=24001373%2C24007246&c=WEB&txp=5436434&n=4ei-1pL34MiCfe-x2&sparams=expire%2Cei%2Cip%2Cid%2Caitags%2Csource%2Crequiressl%2Cgcr%2Cvprv%2Cmime%2Cns%2Cgir%2Cclen%2Cdur%2Clmt&lsparams=mh%2Cmm%2Cmn%2Cms%2Cmv%2Cmvi%2Cpcm2cms%2Cpl%2Cinitcwndbps&lsig=AG3C_xAwRgIhAOSgOy5HXjOjPlgC44_NbmA7S1cJqBVtXcsNFBwpN_U7AiEAzjFYsYIQk8ns6B4wqdDUyPx957kN_emHgLcnh2Hltvs%3D&sig=AOq0QJ8wRgIhAJQl37SckaRPrXtwFvtcBoW4inx50k4m_7ok4z6fPq9xAiEA6OjEBsEm1FptP2mpi9rrgC-5a3IVkMHH5D8AUpNFT0c=", "width": 192, "ext": "mp4", "vcodec": "av01.0.00M.08", "acodec": "none", "vbr": 71.489, "downloader_options": {"http_chunk_size": 10485760}, "container": "mp4_dash", "format": "394 - 192x144 (144p)", "protocol": "https", "http_headers": {"User-Agent": "Mozilla/5.0 (Windows NT 10.0; Win64; x64) AppleWebKit/537.36 (KHTML, like Gecko) Chrome/72.0.3625.2 Safari/537.36", "Accept-Charset": "ISO-8859-1,utf-8;q=0.7,*;q=0.7", "Accept": "text/html,application/xhtml+xml,application/xml;q=0.9,*/*;q=0.8", "Accept-Encoding": "gzip, deflate", "Accept-Language": "en-us,en;q=0.5"}}, {"asr": null, "filesize": 3021020, "format_id": "133", "format_note": "240p", "fps": 30, "height": 240, "quality": 1, "tbr": 97.12, "url": "https://rr5---sn-0opoxu-ihv6.googlevideo.com/videoplayback?expire=1670788115&ei=s9-VY5CYB8evkgb_26GYDw&ip=189.173.225.87&id=o-AHQ4p-kGgRd3_FOPkIXVPI_YrfqyMWJmo5WG4F_abcbD&itag=133&aitags=133%2C134%2C135%2C160%2C242%2C243%2C244%2C278%2C394%2C395%2C396%2C397&source=youtube&requiressl=yes&mh=ma&mm=31%2C29&mn=sn-0opoxu-ihv6%2Csn-q4fl6nsk&ms=au%2Crdu&mv=m&mvi=5&pcm2cms=yes&pl=24&gcr=mx&initcwndbps=907500&vprv=1&mime=video%2Fmp4&ns=CdhfWTqhbbY9pU_riB5P3B8J&gir=yes&clen=3021020&dur=248.848&lmt=1540946239926439&mt=1670766317&fvip=2&keepalive=yes&fexp=24001373%2C24007246&c=WEB&txp=5432432&n=4ei-1pL34MiCfe-x2&sparams=expire%2Cei%2Cip%2Cid%2Caitags%2Csource%2Crequiressl%2Cgcr%2Cvprv%2Cmime%2Cns%2Cgir%2Cclen%2Cdur%2Clmt&lsparams=mh%2Cmm%2Cmn%2Cms%2Cmv%2Cmvi%2Cpcm2cms%2Cpl%2Cinitcwndbps&lsig=AG3C_xAwRQIhANRBLH-u6dbhyMtRhuqRxYQ3kuyjW1Gk5g_n_kI-8DQ7AiAkHZlL1_g4etbLnN1-8j5ikGK24EE233KS4kSFlWBqIQ%3D%3D&sig=AOq0QJ8wRQIgRdoF_DqeepARxIejQSKcJ1u0Cryldx7hlo1erfQcF1ECIQCH-jBZcpsONhMmSFopJ5fCdTojcEaGdF-X5yEWrE3SYw==", "width": 320, "ext": "mp4", "vcodec": "avc1.4d400d", "acodec": "none", "vbr": 97.12, "downloader_options": {"http_chunk_size": 10485760}, "container": "mp4_dash", "format": "133 - 320x240 (240p)", "protocol": "https", "http_headers": {"User-Agent": "Mozilla/5.0 (Windows NT 10.0; Win64; x64) AppleWebKit/537.36 (KHTML, like Gecko) Chrome/72.0.3625.2 Safari/537.36", "Accept-Charset": "ISO-8859-1,utf-8;q=0.7,*;q=0.7", "Accept": "text/html,application/xhtml+xml,application/xml;q=0.9,*/*;q=0.8", "Accept-Encoding": "gzip, deflate", "Accept-Language": "en-us,en;q=0.5"}}, {"asr": null, "filesize": 3848229, "format_id": "395", "format_note": "240p", "fps": 30, "height": 240, "quality": 1, "tbr": 123.713, "url": "https://rr5---sn-0opoxu-ihv6.googlevideo.com/videoplayback?expire=1670788115&ei=s9-VY5CYB8evkgb_26GYDw&ip=189.173.225.87&id=o-AHQ4p-kGgRd3_FOPkIXVPI_YrfqyMWJmo5WG4F_abcbD&itag=395&aitags=133%2C134%2C135%2C160%2C242%2C243%2C244%2C278%2C394%2C395%2C396%2C397&source=youtube&requiressl=yes&mh=ma&mm=31%2C29&mn=sn-0opoxu-ihv6%2Csn-q4fl6nsk&ms=au%2Crdu&mv=m&mvi=5&pcm2cms=yes&pl=24&gcr=mx&initcwndbps=907500&vprv=1&mime=video%2Fmp4&ns=CdhfWTqhbbY9pU_riB5P3B8J&gir=yes&clen=3848229&dur=248.848&lmt=1631309330563445&mt=1670766317&fvip=2&keepalive=yes&fexp=24001373%2C24007246&c=WEB&txp=5436434&n=4ei-1pL34MiCfe-x2&sparams=expire%2Cei%2Cip%2Cid%2Caitags%2Csource%2Crequiressl%2Cgcr%2Cvprv%2Cmime%2Cns%2Cgir%2Cclen%2Cdur%2Clmt&lsparams=mh%2Cmm%2Cmn%2Cms%2Cmv%2Cmvi%2Cpcm2cms%2Cpl%2Cinitcwndbps&lsig=AG3C_xAwRQIgZmzKzhbRmT2NVyu5ugEsVkbE4Az2DupI9GPBrhsCoQ8CIQDjQjdbXK2actOholWC4ERRylAYcTv6nH4aqFigU8eQlQ%3D%3D&sig=AOq0QJ8wRAIgZKNiX6rJD4MUbku80GBeosQbhpGiygl9Bj0o0t0XeNMCIB4tVCx3ZVVCGLz7ZJnkzwE5SGx32e-8wy_jClkvwYUf", "width": 320, "ext": "mp4", "vcodec": "av01.0.00M.08", "acodec": "none", "vbr": 123.713, "downloader_options": {"http_chunk_size": 10485760}, "container": "mp4_dash", "format": "395 - 320x240 (240p)", "protocol": "https", "http_headers": {"User-Agent": "Mozilla/5.0 (Windows NT 10.0; Win64; x64) AppleWebKit/537.36 (KHTML, like Gecko) Chrome/72.0.3625.2 Safari/537.36", "Accept-Charset": "ISO-8859-1,utf-8;q=0.7,*;q=0.7", "Accept": "text/html,application/xhtml+xml,application/xml;q=0.9,*/*;q=0.8", "Accept-Encoding": "gzip, deflate", "Accept-Language": "en-us,en;q=0.5"}}, {"asr": null, "filesize": 4447532, "format_id": "242", "format_note": "240p", "fps": 30, "height": 240, "quality": 1, "tbr": 142.979, "url": "https://rr5---sn-0opoxu-ihv6.googlevideo.com/videoplayback?expire=1670788115&ei=s9-VY5CYB8evkgb_26GYDw&ip=189.173.225.87&id=o-AHQ4p-kGgRd3_FOPkIXVPI_YrfqyMWJmo5WG4F_abcbD&itag=242&aitags=133%2C134%2C135%2C160%2C242%2C243%2C244%2C278%2C394%2C395%2C396%2C397&source=youtube&requiressl=yes&mh=ma&mm=31%2C29&mn=sn-0opoxu-ihv6%2Csn-q4fl6nsk&ms=au%2Crdu&mv=m&mvi=5&pcm2cms=yes&pl=24&gcr=mx&initcwndbps=907500&vprv=1&mime=video%2Fwebm&ns=CdhfWTqhbbY9pU_riB5P3B8J&gir=yes&clen=4447532&dur=248.848&lmt=1540945237279332&mt=1670766317&fvip=2&keepalive=yes&fexp=24001373%2C24007246&c=WEB&txp=5432432&n=4ei-1pL34MiCfe-x2&sparams=expire%2Cei%2Cip%2Cid%2Caitags%2Csource%2Crequiressl%2Cgcr%2Cvprv%2Cmime%2Cns%2Cgir%2Cclen%2Cdur%2Clmt&lsparams=mh%2Cmm%2Cmn%2Cms%2Cmv%2Cmvi%2Cpcm2cms%2Cpl%2Cinitcwndbps&lsig=AG3C_xAwRQIhAI3yshQVCpz-51utN0oFx3oGyBjpdTy8-Vvx8VHgvSFzAiArLKZQw7BTSfrqJPjlH_Ys2nbSK1BmWrG4BLqBsvVV3A%3D%3D&sig=AOq0QJ8wRAIgek2-q7M_egmLOFxY1LKsu2RcamPtnYXy1g9XC1NYZE8CIGoH4DCHmZuFUeZsCr3ckb6e_CK3H-rQDVhzP_GSFJWQ", "width": 320, "ext": "webm", "vcodec": "vp9", "acodec": "none", "vbr": 142.979, "downloader_options": {"http_chunk_size": 10485760}, "container": "webm_dash", "format": "242 - 320x240 (240p)", "protocol": "https", "http_headers": {"User-Agent": "Mozilla/5.0 (Windows NT 10.0; Win64; x64) AppleWebKit/537.36 (KHTML, like Gecko) Chrome/72.0.3625.2 Safari/537.36", "Accept-Charset": "ISO-8859-1,utf-8;q=0.7,*;q=0.7", "Accept": "text/html,application/xhtml+xml,application/xml;q=0.9,*/*;q=0.8", "Accept-Encoding": "gzip, deflate", "Accept-Language": "en-us,en;q=0.5"}}, {"asr": null, "filesize": 6537033, "format_id": "396", "format_note": "360p", "fps": 30, "height": 360, "quality": 2, "tbr": 210.153, "url": "https://rr5---sn-0opoxu-ihv6.googlevideo.com/videoplayback?expire=1670788115&ei=s9-VY5CYB8evkgb_26GYDw&ip=189.173.225.87&id=o-AHQ4p-kGgRd3_FOPkIXVPI_YrfqyMWJmo5WG4F_abcbD&itag=396&aitags=133%2C134%2C135%2C160%2C242%2C243%2C244%2C278%2C394%2C395%2C396%2C397&source=youtube&requiressl=yes&mh=ma&mm=31%2C29&mn=sn-0opoxu-ihv6%2Csn-q4fl6nsk&ms=au%2Crdu&mv=m&mvi=5&pcm2cms=yes&pl=24&gcr=mx&initcwndbps=907500&vprv=1&mime=video%2Fmp4&ns=CdhfWTqhbbY9pU_riB5P3B8J&gir=yes&clen=6537033&dur=248.848&lmt=1631309331698138&mt=1670766317&fvip=2&keepalive=yes&fexp=24001373%2C24007246&c=WEB&txp=5436434&n=4ei-1pL34MiCfe-x2&sparams=expire%2Cei%2Cip%2Cid%2Caitags%2Csource%2Crequiressl%2Cgcr%2Cvprv%2Cmime%2Cns%2Cgir%2Cclen%2Cdur%2Clmt&lsparams=mh%2Cmm%2Cmn%2Cms%2Cmv%2Cmvi%2Cpcm2cms%2Cpl%2Cinitcwndbps&lsig=AG3C_xAwRAIgPXhqwIrbBYkk4K2j_UmapUZoq3-D-X50kJJyYhTM7ckCIGeK_98isdEvTk75mhGwrEx-fch-ItytfV1VISSNK2nW&sig=AOq0QJ8wRQIhAOYG2dKkEPX16fDbevF2K9Iow-OZyuyN1tu8V647FX4nAiBpXws8tfVor8aSa3CYOLR-XiN6jj0wzrC5x0zG81koeA==", "width": 480, "ext": "mp4", "vcodec": "av01.0.01M.08", "acodec": "none", "vbr": 210.153, "downloader_options": {"http_chunk_size": 10485760}, "container": "mp4_dash", "format": "396 - 480x360 (360p)", "protocol": "https", "http_headers": {"User-Agent": "Mozilla/5.0 (Windows NT 10.0; Win64; x64) AppleWebKit/537.36 (KHTML, like Gecko) Chrome/72.0.3625.2 Safari/537.36", "Accept-Charset": "ISO-8859-1,utf-8;q=0.7,*;q=0.7", "Accept": "text/html,application/xhtml+xml,application/xml;q=0.9,*/*;q=0.8", "Accept-Encoding": "gzip, deflate", "Accept-Language": "en-us,en;q=0.5"}}, {"asr": null, "filesize": 7033308, "format_id": "134", "format_note": "360p", "fps": 30, "height": 360, "quality": 2, "tbr": 226.107, "url": "https://rr5---sn-0opoxu-ihv6.googlevideo.com/videoplayback?expire=1670788115&ei=s9-VY5CYB8evkgb_26GYDw&ip=189.173.225.87&id=o-AHQ4p-kGgRd3_FOPkIXVPI_YrfqyMWJmo5WG4F_abcbD&itag=134&aitags=133%2C134%2C135%2C160%2C242%2C243%2C244%2C278%2C394%2C395%2C396%2C397&source=youtube&requiressl=yes&mh=ma&mm=31%2C29&mn=sn-0opoxu-ihv6%2Csn-q4fl6nsk&ms=au%2Crdu&mv=m&mvi=5&pcm2cms=yes&pl=24&gcr=mx&initcwndbps=907500&vprv=1&mime=video%2Fmp4&ns=CdhfWTqhbbY9pU_riB5P3B8J&gir=yes&clen=7033308&dur=248.848&lmt=1540946232599256&mt=1670766317&fvip=2&keepalive=yes&fexp=24001373%2C24007246&c=WEB&txp=5432432&n=4ei-1pL34MiCfe-x2&sparams=expire%2Cei%2Cip%2Cid%2Caitags%2Csource%2Crequiressl%2Cgcr%2Cvprv%2Cmime%2Cns%2Cgir%2Cclen%2Cdur%2Clmt&lsparams=mh%2Cmm%2Cmn%2Cms%2Cmv%2Cmvi%2Cpcm2cms%2Cpl%2Cinitcwndbps&lsig=AG3C_xAwRgIhANNVJcSJv7V3f6ll8BARgGWPxsW_8Oh6uVa9LBey6vPtAiEAweHDzywJxbVuFret3SbXRp0oPvYd8rJ5b1KPGQk0TDI%3D&sig=AOq0QJ8wRgIhALtaAnYin2IaaaSJtIAJH8wIm4Nkiu_SWyzECNOaUfzuAiEA79scfBrIAejNqvBx6r9YxaSLQtgTkPHKBcuXJtSfS7I=", "width": 480, "ext": "mp4", "vcodec": "avc1.4d401e", "acodec": "none", "vbr": 226.107, "downloader_options": {"http_chunk_size": 10485760}, "container": "mp4_dash", "format": "134 - 480x360 (360p)", "protocol": "https", "http_headers": {"User-Agent": "Mozilla/5.0 (Windows NT 10.0; Win64; x64) AppleWebKit/537.36 (KHTML, like Gecko) Chrome/72.0.3625.2 Safari/537.36", "Accept-Charset": "ISO-8859-1,utf-8;q=0.7,*;q=0.7", "Accept": "text/html,application/xhtml+xml,application/xml;q=0.9,*/*;q=0.8", "Accept-Encoding": "gzip, deflate", "Accept-Language": "en-us,en;q=0.5"}}, {"asr": null, "filesize": 7737387, "format_id": "243", "format_note": "360p", "fps": 30, "height": 360, "quality": 2, "tbr": 248.742, "url": "https://rr5---sn-0opoxu-ihv6.googlevideo.com/videoplayback?expire=1670788115&ei=s9-VY5CYB8evkgb_26GYDw&ip=189.173.225.87&id=o-AHQ4p-kGgRd3_FOPkIXVPI_YrfqyMWJmo5WG4F_abcbD&itag=243&aitags=133%2C134%2C135%2C160%2C242%2C243%2C244%2C278%2C394%2C395%2C396%2C397&source=youtube&requiressl=yes&mh=ma&mm=31%2C29&mn=sn-0opoxu-ihv6%2Csn-q4fl6nsk&ms=au%2Crdu&mv=m&mvi=5&pcm2cms=yes&pl=24&gcr=mx&initcwndbps=907500&vprv=1&mime=video%2Fwebm&ns=CdhfWTqhbbY9pU_riB5P3B8J&gir=yes&clen=7737387&dur=248.848&lmt=1540945236993458&mt=1670766317&fvip=2&keepalive=yes&fexp=24001373%2C24007246&c=WEB&txp=5432432&n=4ei-1pL34MiCfe-x2&sparams=expire%2Cei%2Cip%2Cid%2Caitags%2Csource%2Crequiressl%2Cgcr%2Cvprv%2Cmime%2Cns%2Cgir%2Cclen%2Cdur%2Clmt&lsparams=mh%2Cmm%2Cmn%2Cms%2Cmv%2Cmvi%2Cpcm2cms%2Cpl%2Cinitcwndbps&lsig=AG3C_xAwRAIgVQ_KSw371gT8YlaEdUxsoN0IDRnqJk-adegwZnMQojMCIEYu1qb9H5guiorhd6z3q6VPK1hEyztY-Jvv-yoIjXD5&sig=AOq0QJ8wRQIhAM_ep-l3L574_vxflhblCfVqzCikxh-e_5Rsv5L4qOtUAiBSdOUySrjBZvK2m9scg72SGzauLSCruKPax8hIPqK7JQ==", "width": 480, "ext": "webm", "vcodec": "vp9", "acodec": "none", "vbr": 248.742, "downloader_options": {"http_chunk_size": 10485760}, "container": "webm_dash", "format": "243 - 480x360 (360p)", "protocol": "https", "http_headers": {"User-Agent": "Mozilla/5.0 (Windows NT 10.0; Win64; x64) AppleWebKit/537.36 (KHTML, like Gecko) Chrome/72.0.3625.2 Safari/537.36", "Accept-Charset": "ISO-8859-1,utf-8;q=0.7,*;q=0.7", "Accept": "text/html,application/xhtml+xml,application/xml;q=0.9,*/*;q=0.8", "Accept-Encoding": "gzip, deflate", "Accept-Language": "en-us,en;q=0.5"}}, {"asr": null, "filesize": 10815281, "format_id": "397", "format_note": "480p", "fps": 30, "height": 480, "quality": 3, "tbr": 347.691, "url": "https://rr5---sn-0opoxu-ihv6.googlevideo.com/videoplayback?expire=1670788115&ei=s9-VY5CYB8evkgb_26GYDw&ip=189.173.225.87&id=o-AHQ4p-kGgRd3_FOPkIXVPI_YrfqyMWJmo5WG4F_abcbD&itag=397&aitags=133%2C134%2C135%2C160%2C242%2C243%2C244%2C278%2C394%2C395%2C396%2C397&source=youtube&requiressl=yes&mh=ma&mm=31%2C29&mn=sn-0opoxu-ihv6%2Csn-q4fl6nsk&ms=au%2Crdu&mv=m&mvi=5&pcm2cms=yes&pl=24&gcr=mx&initcwndbps=907500&vprv=1&mime=video%2Fmp4&ns=CdhfWTqhbbY9pU_riB5P3B8J&gir=yes&clen=10815281&dur=248.848&lmt=1631309330612893&mt=1670766317&fvip=2&keepalive=yes&fexp=24001373%2C24007246&c=WEB&txp=5436434&n=4ei-1pL34MiCfe-x2&sparams=expire%2Cei%2Cip%2Cid%2Caitags%2Csource%2Crequiressl%2Cgcr%2Cvprv%2Cmime%2Cns%2Cgir%2Cclen%2Cdur%2Clmt&lsparams=mh%2Cmm%2Cmn%2Cms%2Cmv%2Cmvi%2Cpcm2cms%2Cpl%2Cinitcwndbps&lsig=AG3C_xAwRQIgblNXoUT6q9D7FG8Bah9UAfzXShHuOZ4vzu3s1gAc3eQCIQDvkjm6oeSrDtmoH25eGu6Mf3uNPgavPwhFq2GPjZB2Tw%3D%3D&sig=AOq0QJ8wRQIhALhQofmVfXnorldX87yWhtzdVjJwy9CveIHzqOtSzTa4AiADJwF4w9auIlwPVx1LINxqw3hMRKISG8WhGxJ1q30ZPw==", "width": 640, "ext": "mp4", "vcodec": "av01.0.04M.08", "acodec": "none", "vbr": 347.691, "downloader_options": {"http_chunk_size": 10485760}, "container": "mp4_dash", "format": "397 - 640x480 (480p)", "protocol": "https", "http_headers": {"User-Agent": "Mozilla/5.0 (Windows NT 10.0; Win64; x64) AppleWebKit/537.36 (KHTML, like Gecko) Chrome/72.0.3625.2 Safari/537.36", "Accept-Charset": "ISO-8859-1,utf-8;q=0.7,*;q=0.7", "Accept": "text/html,application/xhtml+xml,application/xml;q=0.9,*/*;q=0.8", "Accept-Encoding": "gzip, deflate", "Accept-Language": "en-us,en;q=0.5"}}, {"asr": null, "filesize": 12589152, "format_id": "244", "format_note": "480p", "fps": 30, "height": 480, "quality": 3, "tbr": 404.717, "url": "https://rr5---sn-0opoxu-ihv6.googlevideo.com/videoplayback?expire=1670788115&ei=s9-VY5CYB8evkgb_26GYDw&ip=189.173.225.87&id=o-AHQ4p-kGgRd3_FOPkIXVPI_YrfqyMWJmo5WG4F_abcbD&itag=244&aitags=133%2C134%2C135%2C160%2C242%2C243%2C244%2C278%2C394%2C395%2C396%2C397&source=youtube&requiressl=yes&mh=ma&mm=31%2C29&mn=sn-0opoxu-ihv6%2Csn-q4fl6nsk&ms=au%2Crdu&mv=m&mvi=5&pcm2cms=yes&pl=24&gcr=mx&initcwndbps=907500&vprv=1&mime=video%2Fwebm&ns=CdhfWTqhbbY9pU_riB5P3B8J&gir=yes&clen=12589152&dur=248.848&lmt=1540945236981241&mt=1670766317&fvip=2&keepalive=yes&fexp=24001373%2C24007246&c=WEB&txp=5432432&n=4ei-1pL34MiCfe-x2&sparams=expire%2Cei%2Cip%2Cid%2Caitags%2Csource%2Crequiressl%2Cgcr%2Cvprv%2Cmime%2Cns%2Cgir%2Cclen%2Cdur%2Clmt&lsparams=mh%2Cmm%2Cmn%2Cms%2Cmv%2Cmvi%2Cpcm2cms%2Cpl%2Cinitcwndbps&lsig=AG3C_xAwRQIgDoN45aijZM1Tv6YXLni9rKRYaLFBjnRxKEbyR0La-kgCIQCjamPvZqhkkQ6oaybOC84-3ucnvVekUbXaA7WY6exTKQ%3D%3D&sig=AOq0QJ8wRAIgQfKZf1jfn3lUnBRcimg2eH8uPe9ohwg4XG7wCnrYxW8CIG3IuSZddpsUHPe4saULVCu_L-9cifOcAxt5_80OCaTr", "width": 640, "ext": "webm", "vcodec": "vp9", "acodec": "none", "vbr": 404.717, "downloader_options": {"http_chunk_size": 10485760}, "container": "webm_dash", "format": "244 - 640x480 (480p)", "protocol": "https", "http_headers": {"User-Agent": "Mozilla/5.0 (Windows NT 10.0; Win64; x64) AppleWebKit/537.36 (KHTML, like Gecko) Chrome/72.0.3625.2 Safari/537.36", "Accept-Charset": "ISO-8859-1,utf-8;q=0.7,*;q=0.7", "Accept": "text/html,application/xhtml+xml,application/xml;q=0.9,*/*;q=0.8", "Accept-Encoding": "gzip, deflate", "Accept-Language": "en-us,en;q=0.5"}}, {"asr": null, "filesize": 13038191, "format_id": "135", "format_note": "480p", "fps": 30, "height": 480, "quality": 3, "tbr": 419.153, "url": "https://rr5---sn-0opoxu-ihv6.googlevideo.com/videoplayback?expire=1670788115&ei=s9-VY5CYB8evkgb_26GYDw&ip=189.173.225.87&id=o-AHQ4p-kGgRd3_FOPkIXVPI_YrfqyMWJmo5WG4F_abcbD&itag=135&aitags=133%2C134%2C135%2C160%2C242%2C243%2C244%2C278%2C394%2C395%2C396%2C397&source=youtube&requiressl=yes&mh=ma&mm=31%2C29&mn=sn-0opoxu-ihv6%2Csn-q4fl6nsk&ms=au%2Crdu&mv=m&mvi=5&pcm2cms=yes&pl=24&gcr=mx&initcwndbps=907500&vprv=1&mime=video%2Fmp4&ns=CdhfWTqhbbY9pU_riB5P3B8J&gir=yes&clen=13038191&dur=248.848&lmt=1540945194726026&mt=1670766317&fvip=2&keepalive=yes&fexp=24001373%2C24007246&c=WEB&txp=5432432&n=4ei-1pL34MiCfe-x2&sparams=expire%2Cei%2Cip%2Cid%2Caitags%2Csource%2Crequiressl%2Cgcr%2Cvprv%2Cmime%2Cns%2Cgir%2Cclen%2Cdur%2Clmt&lsparams=mh%2Cmm%2Cmn%2Cms%2Cmv%2Cmvi%2Cpcm2cms%2Cpl%2Cinitcwndbps&lsig=AG3C_xAwRAIgU9LyCvfjuGU59DcGE9j-X4BqPfwBFld4Z8MaQgsD8NsCIFud3qns8MPznSk_K4ug4E4d5tF1HtR5qmMMjOFTU3bg&sig=AOq0QJ8wRQIgexTwchvSxQGwnjzhkOVJqtnEx_PDdEtrbK4BkW2IKN4CIQDKxMBE5JkcaKQYtOUVhChHGm2miGuPv4ZeO7XGaXfRsw==", "width": 640, "ext": "mp4", "vcodec": "avc1.4d401e", "acodec": "none", "vbr": 419.153, "downloader_options": {"http_chunk_size": 10485760}, "container": "mp4_dash", "format": "135 - 640x480 (480p)", "protocol": "https", "http_headers": {"User-Agent": "Mozilla/5.0 (Windows NT 10.0; Win64; x64) AppleWebKit/537.36 (KHTML, like Gecko) Chrome/72.0.3625.2 Safari/537.36", "Accept-Charset": "ISO-8859-1,utf-8;q=0.7,*;q=0.7", "Accept": "text/html,application/xhtml+xml,application/xml;q=0.9,*/*;q=0.8", "Accept-Encoding": "gzip, deflate", "Accept-Language": "en-us,en;q=0.5"}}, {"asr": 44100, "filesize": null, "format_id": "18", "format_note": "360p", "fps": 30, "height": 360, "quality": 2, "tbr": 352.667, "url": "https://rr5---sn-0opoxu-ihv6.googlevideo.com/videoplayback?expire=1670788115&ei=s9-VY5CYB8evkgb_26GYDw&ip=189.173.225.87&id=o-AHQ4p-kGgRd3_FOPkIXVPI_YrfqyMWJmo5WG4F_abcbD&itag=18&source=youtube&requiressl=yes&mh=ma&mm=31%2C29&mn=sn-0opoxu-ihv6%2Csn-q4fl6nsk&ms=au%2Crdu&mv=m&mvi=5&pcm2cms=yes&pl=24&gcr=mx&initcwndbps=907500&vprv=1&mime=video%2Fmp4&ns=tfeDDIfvqE5Y5xsAn3S3UWMJ&cnr=14&ratebypass=yes&dur=248.917&lmt=1664170977274551&mt=1670766317&fvip=2&fexp=24001373%2C24007246&c=WEB&txp=5438434&n=smxiBnze7U4oeezX6&sparams=expire%2Cei%2Cip%2Cid%2Citag%2Csource%2Crequiressl%2Cgcr%2Cvprv%2Cmime%2Cns%2Ccnr%2Cratebypass%2Cdur%2Clmt&lsparams=mh%2Cmm%2Cmn%2Cms%2Cmv%2Cmvi%2Cpcm2cms%2Cpl%2Cinitcwndbps&lsig=AG3C_xAwRAIgW_QK8bF7pFZob4xK-CQl_3Idej3ymcd41yf5j51mI30CIDugvsEnqbNFoNUKGgSzzv5VPrzs0Bs87eDNL3A9rYDr&sig=AOq0QJ8wRgIhAM91AqjsbnAYRMOaJNHh85IVPfplbKsvjHMgVGSxzh53AiEA7H6-aa4Xm_d-kgtcHwCRGvlOuM5Dbgo-tNs-5_qfghk=", "width": 480, "ext": "mp4", "vcodec": "avc1.42001E", "acodec": "mp4a.40.2", "format": "18 - 480x360 (360p)", "protocol": "https", "http_headers": {"User-Agent": "Mozilla/5.0 (Windows NT 10.0; Win64; x64) AppleWebKit/537.36 (KHTML, like Gecko) Chrome/72.0.3625.2 Safari/537.36", "Accept-Charset": "ISO-8859-1,utf-8;q=0.7,*;q=0.7", "Accept": "text/html,application/xhtml+xml,application/xml;q=0.9,*/*;q=0.8", "Accept-Encoding": "gzip, deflate", "Accept-Language": "en-us,en;q=0.5"}}], "thumbnails": [{"height": 94, "url": "https://i.ytimg.com/vi/TMY9Wrh1oPA/hqdefault.jpg?sqp=-oaymwEbCKgBEF5IVfKriqkDDggBFQAAiEIYAXABwAEG&rs=AOn4CLBluiSsiitumrxVuwwMWlAnIs_wTg", "width": 168, "resolution": "168x94", "id": "0"}, {"height": 110, "url": "https://i.ytimg.com/vi/TMY9Wrh1oPA/hqdefault.jpg?sqp=-oaymwEbCMQBEG5IVfKriqkDDggBFQAAiEIYAXABwAEG&rs=AOn4CLCM7rJE1zIOd7jtREirvWrCrlx8pQ", "width": 196, "resolution": "196x110", "id": "1"}, {"height": 138, "url": "https://i.ytimg.com/vi/TMY9Wrh1oPA/hqdefault.jpg?sqp=-oaymwEcCPYBEIoBSFXyq4qpAw4IARUAAIhCGAFwAcABBg==&rs=AOn4CLCGVxUq3Z5ZS5GkIeAy3KAK2BR73w", "width": 246, "resolution": "246x138", "id": "2"}, {"height": 188, "url": "https://i.ytimg.com/vi/TMY9Wrh1oPA/hqdefault.jpg?sqp=-oaymwEcCNACELwBSFXyq4qpAw4IARUAAIhCGAFwAcABBg==&rs=AOn4CLB06FxdEDtxy6OGG5r4b3psj-DV1A", "width": 336, "resolution": "336x188", "id": "3"}, {"height": 1080, "url": "https://i.ytimg.com/vi/TMY9Wrh1oPA/maxresdefault.jpg", "width": 1920, "resolution": "1920x1080", "id": "4"}], "description": "Music video by Stevie Ray Vaughan And Double Trouble performing Change It. (C) 1985 Sony BMG Music Entertainment", "upload_date": "20091124", "uploader": "stevierayvaughnVEVO", "uploader_id": "stevierayvaughnVEVO", "uploader_url": "http://www.youtube.com/user/stevierayvaughnVEVO", "channel_id": "UCX25kfBbEN1MNEPtlNLOycw", "channel_url": "https://www.youtube.com/channel/UCX25kfBbEN1MNEPtlNLOycw", "duration": 249, "view_count": 1855375, "average_rating": null, "age_limit": 0, "webpage_url": "https://www.youtube.com/watch?v=TMY9Wrh1oPA", "categories": ["Music"], "tags": ["Change It", "Epic/Legacy", "Pop", "Stevie Ray Vaughan Double Trouble"], "is_live": null, "channel": "Stevie Ray Vaughan", "extractor": "youtube", "webpage_url_basename": "watch", "extractor_key": "Youtube", "playlist": null, "playlist_index": null, "thumbnail": "https://i.ytimg.com/vi/TMY9Wrh1oPA/maxresdefault.jpg", "display_id": "TMY9Wrh1oPA", "asr": 44100, "filesize": null, "format_id": "18", "format_note": "360p", "fps": 30, "height": 360, "quality": 2, "tbr": 352.667, "url": "https://rr5---sn-0opoxu-ihv6.googlevideo.com/videoplayback?expire=1670788115&ei=s9-VY5CYB8evkgb_26GYDw&ip=189.173.225.87&id=o-AHQ4p-kGgRd3_FOPkIXVPI_YrfqyMWJmo5WG4F_abcbD&itag=18&source=youtube&requiressl=yes&mh=ma&mm=31%2C29&mn=sn-0opoxu-ihv6%2Csn-q4fl6nsk&ms=au%2Crdu&mv=m&mvi=5&pcm2cms=yes&pl=24&gcr=mx&initcwndbps=907500&vprv=1&mime=video%2Fmp4&ns=tfeDDIfvqE5Y5xsAn3S3UWMJ&cnr=14&ratebypass=yes&dur=248.917&lmt=1664170977274551&mt=1670766317&fvip=2&fexp=24001373%2C24007246&c=WEB&txp=5438434&n=smxiBnze7U4oeezX6&sparams=expire%2Cei%2Cip%2Cid%2Citag%2Csource%2Crequiressl%2Cgcr%2Cvprv%2Cmime%2Cns%2Ccnr%2Cratebypass%2Cdur%2Clmt&lsparams=mh%2Cmm%2Cmn%2Cms%2Cmv%2Cmvi%2Cpcm2cms%2Cpl%2Cinitcwndbps&lsig=AG3C_xAwRAIgW_QK8bF7pFZob4xK-CQl_3Idej3ymcd41yf5j51mI30CIDugvsEnqbNFoNUKGgSzzv5VPrzs0Bs87eDNL3A9rYDr&sig=AOq0QJ8wRgIhAM91AqjsbnAYRMOaJNHh85IVPfplbKsvjHMgVGSxzh53AiEA7H6-aa4Xm_d-kgtcHwCRGvlOuM5Dbgo-tNs-5_qfghk=", "width": 480, "ext": "mp4", "vcodec": "avc1.42001E", "acodec": "mp4a.40.2", "format": "18 - 480x360 (360p)", "protocol": "https", "http_headers": {"User-Agent": "Mozilla/5.0 (Windows NT 10.0; Win64; x64) AppleWebKit/537.36 (KHTML, like Gecko) Chrome/72.0.3625.2 Safari/537.36", "Accept-Charset": "ISO-8859-1,utf-8;q=0.7,*;q=0.7", "Accept": "text/html,application/xhtml+xml,application/xml;q=0.9,*/*;q=0.8", "Accept-Encoding": "gzip, deflate", "Accept-Language": "en-us,en;q=0.5"}, "fulltitle": "Stevie Ray Vaughan & Double Trouble - Change It (Video)", "_filename": "Stevie Ray Vaughan & Double Trouble - Change It (Video)-TMY9Wrh1oPA.mp4"}